{"name":"Architectural Lighting and Design Management","applicationDeadlines":[{"date":"2017-08-30T00:00:00.000Z","international":false,"type":"winter"}],"university":"Hochschule Wismar","direction":{"degree":"ma","direction":["practical"],"masterType":"studyingFurther"},"topicAndFocus":{"topicFocus":"fachspezifisch","functionalComposition":"artAndNonArt","allowedDisciplines":"Design, Innenarchitektur, Architektur, Elektrotechnik","allowedDisciplinesTag":["room","product"]},"timeAndMoney":{"allowedForms":["remote","partTime"],"costs":3900,"semester":"4"},"internationality":{"mainLanguages":["english"],"semesterAbroad":"yes","doubleDegree":false},"metadata":{"website":"https://www.wings.hs-wismar.de/de/fernstudium_master/lighting_design","facebook":"https://www.facebook.com/WingsFernstudium","instagram":null,"twitter":"https://twitter.com/WingsStudium"}}