{
  "name": "Industrial Design ",
  "universityName": "Burg Giebichenstein Kunsthochschule Halle",
  "universityDetails": {
    "otherUniversity": "nein",
    "department": "Design"
  },
  "direction": {
    "degree": "ma",
    "direction": [
      "practical"
    ],
    "masterType": "consecutive"
  },
  "topicAndFocus": {
    "topicFocus": "fachspezifisch",
    "functionalComposition": "disciplinary",
    "allowedDisciplines": "Vorrangig gestalterisch-künstlerische Disziplinen mit vergleichbarer inhaltlicher Ausrichtung",
    "allowedDisciplinesTag": [
      "product"
    ]
  },
  "timeAndMoney": {
    "applicationDeadlines": [
      {
        "type": "summer",
        "date": "2019-05-15T00:00:00.000Z",
        "international": false
      }
    ],
    "allowedForms": [
      "fullTime"
    ],
    "costs": 0,
    "semester": "2–4"
  },
  "internationality": {
    "mainLanguages": [
      "german"
    ],
    "semesterAbroad": "no",
    "doubleDegree": false
  },
  "metadata": {
    "website": "http://www.burg-halle.de/design/industrial-design-ma/industrial-design/",
    "facebook": "https://www.facebook.com/burghalle/",
    "instagram": "https://www.instagram.com/burg_halle/",
    "twitter": "https://twitter.com/burghalle"
  }
}