{
  "name": "Design Interaktiver Medien",
  "universityName": "Hochschule Furtwangen",
  "universityDetails": {
    "otherUniversity": "nein",
    "department": "Digitale Medien"
  },
  "direction": {
    "degree": "ma",
    "direction": [
      "practical"
    ],
    "masterType": "consecutive"
  },
  "topicAndFocus": {
    "topicFocus": "fachspezifisch",
    "functionalComposition": "interdisciplinaryArt",
    "allowedDisciplines": "Medien- und/oder designorientiert",
    "allowedDisciplinesTag": [
      "digital",
      "filmAndPhotograpy"
    ]
  },
  "timeAndMoney": {
    "applicationDeadlines": [
      {
        "type": "winter",
        "date": "2019-07-15T16:27:48.549Z",
        "international": false
      },
      {
        "type": "summer",
        "international": false,
        "date": "2024-01-15T16:18:54.299Z"
      }
    ],
    "allowedForms": [
      "fullTime"
    ],
    "costs": 0,
    "semester": "3"
  },
  "internationality": {
    "mainLanguages": [
      "german"
    ],
    "semesterAbroad": "no",
    "doubleDegree": false
  },
  "metadata": {
    "website": "https://www.hs-furtwangen.de/zukunft-studieren/studiengaenge/design-interaktiver-medien-master",
    "facebook": "https://www.facebook.com/DigitaleMedien.Furtwangen",
    "instagram": "https://www.instagram.com/digitalemedienfurtwangen/",
    "twitter": "https://twitter.com/hs_furtwangen"
  }
}